Metadata-Version: 1.0
Name: zstat-cli
Version: 0.1.4
Summary: Bone-simple tool for generating basic numerical stats from stdin
Home-page: https://github.com/zdwolfe/zstat
Author: Zachary Wolfe
Author-email: wolfe.zach@gmail.com
License: MIT
Platform: UNKNOWN
